chainjacking/__init__.py
chainjacking/__main__.py
chainjacking/chainjacking.py
chainjacking-1.1.2.dist-info/LICENSE.txt
chainjacking-1.1.2.dist-info/METADATA
chainjacking-1.1.2.dist-info/WHEEL
chainjacking-1.1.2.dist-info/top_level.txt
chainjacking-1.1.2.dist-info/RECORD
