Metadata-Version: 2.1
Name: chainjacking
Version: 1.1.2
Summary: A tool to scan your direct GitHub dependencies for Go and find ones susceptible to ChainJacking attack
Home-page: https://github.com/checkmarx/chainjacking
Author: Checkmarx
Author-email: lior.kaplan@checkmarx.com
License: Apache v2
Keywords: chainjacking,supply chain,go,checkmarx
Platform: UNKNOWN
Requires-Python: >=3.6
License-File: LICENSE.txt
Requires-Dist: requests (>=2.25.1)
